setup.cfg
setup.py
scoria_mda/AtomsAndBonds.py
scoria_mda/FileIO.py
scoria_mda/Geometry.py
scoria_mda/Information.py
scoria_mda/Manipulation.py
scoria_mda/Molecule.py
scoria_mda/OtherMolecules.py
scoria_mda/Quaternion.py
scoria_mda/Selections.py
scoria_mda/Test.py
scoria_mda/__init__.py
scoria_mda/__main__.py
scoria_mda/six.py
scoria_mda.egg-info/PKG-INFO
scoria_mda.egg-info/SOURCES.txt
scoria_mda.egg-info/dependency_links.txt
scoria_mda.egg-info/requires.txt
scoria_mda.egg-info/top_level.txt
scoria_mda/dumbpy/Array.py
scoria_mda/dumbpy/DType.py
scoria_mda/dumbpy/Support.py
scoria_mda/dumbpy/Utils.py
scoria_mda/dumbpy/__init__.py
scoria_mda/sample-files/3_mol_test.pdb
scoria_mda/sample-files/DNA_RNA_Protein.pdb
scoria_mda/sample-files/M2_traj.dcd
scoria_mda/sample-files/M2_traj.psf
scoria_mda/sample-files/file_io_test.pdb
scoria_mda/sample-files/other_mol_test.pdb
scoria_mda/sample-files/single_frame.100.dcd
scoria_mda/sample-files/single_frame.dcd
scoria_mda/sample-files/single_frame.pdb
scoria_mda/sample-files/single_frame.pdbqt
scoria_mda/sample-files/single_frame.psf
scoria_mda/sample-files/test_sim.dcd
scoria_mda/sample-files/test_sim.pdb
scoria_mda/sample-files/test_sim.psf
scoria_mda/unittests/FileIOTests.py
scoria_mda/unittests/GeometryTests.py
scoria_mda/unittests/InformationTests.py
scoria_mda/unittests/ManipulationTests.py
scoria_mda/unittests/OtherMoleculeTests.py
scoria_mda/unittests/QuarternionTests.py
scoria_mda/unittests/SelectionTests.py
scoria_mda/unittests/UnitTests.py
scoria_mda/unittests/__init__.py